[
  {
    "id": 1,
    "name": "Battalion 1",
    "sport": "Football",
    "division": "Premier League",
    "organisation_id": 1,
    "organisation_name": "Medinah FC",
    "is_active": true,
    "is_locked": false,
    "parent_squad_id": null,
    "squad_type": "Senior",
    "season": "2023-24",
    "coach": "Roberto Martinez",
    "assistant_coach": "Sarah Johnson",
    "captain": "James Wilson",
    "vice_captain": "Elena Rodriguez",
    "formation": "4-3-3",
    "home_venue": "Home Stadium",
    "training_ground": "Training Center A",
    "squad_size": 25,
    "active_players": 20,
    "injured_players": 2,
    "suspended_players": 0,
    "stats": {
      "matches_played": 18,
      "wins": 11,
      "draws": 4,
      "losses": 3,
      "goals_for": 34,
      "goals_against": 18,
      "points": 37,
      "league_position": 4
    },
    "players": [
      {
        "athlete_id": 1,
        "name": "Marcus Johnson",
        "position": "Forward",
        "jersey_number": 9,
        "status": "Active"
      },
      {
        "athlete_id": 2,
        "name": "Elena Rodriguez",
        "position": "Midfielder",
        "jersey_number": 8,
        "status": "Injured"
      },
      {
        "athlete_id": 3,
        "name": "David Chen",
        "position": "Defender",
        "jersey_number": 5,
        "status": "Active"
      },
      {
        "athlete_id": 4,
        "name": "Sarah Williams",
        "position": "Goalkeeper",
        "jersey_number": 1,
        "status": "Active"
      },
      {
        "athlete_id": 6,
        "name": "Emma Davis",
        "position": "Midfielder",
        "jersey_number": 10,
        "status": "Active"
      },
      {
        "athlete_id": 7,
        "name": "James Wilson",
        "position": "Defender",
        "jersey_number": 4,
        "status": "Active"
      }
    ],
    "recent_form": ["W", "W", "D", "L", "W"],
    "next_match": {
      "date": "2024-01-18",
      "opponent": "Liverpool FC",
      "opponent_logo": "liverpool",
      "venue": "Away",
      "competition": "Premier League"
    },
    "logo": "arsenal",
    "league": "premier-league",
    "created_at": "2023-07-01T10:00:00Z",
    "updated_at": "2024-01-15T14:30:00Z"
  },
  {
    "id": 2,
    "name": "Battalion 2",
    "sport": "Football",
    "division": "Championship",
    "organisation_id": 1,
    "organisation_name": "Medinah FC",
    "is_active": true,
    "is_locked": false,
    "parent_squad_id": 1,
    "squad_type": "Reserve",
    "season": "2023-24",
    "coach": "Alex Thompson",
    "assistant_coach": "Mike Stevens",
    "captain": "Alex Thompson",
    "vice_captain": "Maria Santos",
    "formation": "4-4-2",
    "home_venue": "Training Ground Stadium",
    "training_ground": "Training Center B",
    "squad_size": 20,
    "active_players": 16,
    "injured_players": 1,
    "suspended_players": 0,
    "stats": {
      "matches_played": 15,
      "wins": 8,
      "draws": 5,
      "losses": 2,
      "goals_for": 28,
      "goals_against": 15,
      "points": 29,
      "league_position": 6
    },
    "players": [
      {
        "athlete_id": 5,
        "name": "Alex Thompson",
        "position": "Forward",
        "jersey_number": 11,
        "status": "Active"
      },
      {
        "athlete_id": 8,
        "name": "Maria Santos",
        "position": "Forward",
        "jersey_number": 7,
        "status": "Active"
      }
    ],
    "recent_form": ["W", "D", "W", "W", "D"],
    "next_match": {
      "date": "2024-01-16",
      "opponent": "Brighton Reserves",
      "opponent_logo": "brighton",
      "venue": "Home",
      "competition": "Reserve League"
    },
    "logo": "chelsea",
    "league": "premier-league",
    "created_at": "2023-07-01T10:00:00Z",
    "updated_at": "2024-01-15T14:30:00Z"
  },
  {
    "id": 3,
    "name": "Battalion 3",
    "sport": "Football",
    "division": "Youth League",
    "organisation_id": 1,
    "organisation_name": "Medinah FC",
    "is_active": true,
    "is_locked": false,
    "parent_squad_id": 1,
    "squad_type": "Youth",
    "season": "2023-24",
    "coach": "Tom Mitchell",
    "assistant_coach": "Jenny Adams",
    "captain": "Ryan Murphy",
    "vice_captain": "Sophie Clarke",
    "formation": "4-2-3-1",
    "home_venue": "Academy Stadium",
    "training_ground": "Youth Academy",
    "squad_size": 18,
    "active_players": 18,
    "injured_players": 0,
    "suspended_players": 0,
    "stats": {
      "matches_played": 12,
      "wins": 9,
      "draws": 2,
      "losses": 1,
      "goals_for": 31,
      "goals_against": 12,
      "points": 29,
      "league_position": 2
    },
    "players": [
      {
        "athlete_id": 9,
        "name": "Ryan Murphy",
        "position": "Midfielder",
        "jersey_number": 6,
        "status": "Active"
      },
      {
        "athlete_id": 10,
        "name": "Sophie Clarke",
        "position": "Defender",
        "jersey_number": 3,
        "status": "Active"
      }
    ],
    "recent_form": ["W", "W", "D", "W", "W"],
    "next_match": {
      "date": "2024-01-17",
      "opponent": "Arsenal Youth",
      "opponent_logo": "arsenal",
      "venue": "Away",
      "competition": "Youth League"
    },
    "logo": "manchester-united",
    "league": "premier-league",
    "created_at": "2023-07-01T10:00:00Z",
    "updated_at": "2024-01-15T14:30:00Z"
  },
  {
    "id": 4,
    "name": "Company 1",
    "sport": "Football",
    "division": "Women's Super League",
    "organisation_id": 1,
    "organisation_name": "Medinah FC",
    "is_active": true,
    "is_locked": false,
    "parent_squad_id": null,
    "squad_type": "Women's",
    "season": "2023-24",
    "coach": "Lisa Rodriguez",
    "assistant_coach": "Kate Wilson",
    "captain": "Emma Thompson",
    "vice_captain": "Amy Johnson",
    "formation": "4-3-3",
    "home_venue": "Women's Stadium",
    "training_ground": "Training Center C",
    "squad_size": 23,
    "active_players": 20,
    "injured_players": 1,
    "suspended_players": 0,
    "stats": {
      "matches_played": 14,
      "wins": 10,
      "draws": 3,
      "losses": 1,
      "goals_for": 42,
      "goals_against": 8,
      "points": 33,
      "league_position": 1
    },
    "players": [
      {
        "athlete_id": 11,
        "name": "Emma Thompson",
        "position": "Forward",
        "jersey_number": 10,
        "status": "Active"
      },
      {
        "athlete_id": 12,
        "name": "Amy Johnson",
        "position": "Midfielder",
        "jersey_number": 8,
        "status": "Active"
      }
    ],
    "recent_form": ["W", "W", "W", "D", "W"],
    "next_match": {
      "date": "2024-01-19",
      "opponent": "Chelsea Women",
      "opponent_logo": "chelsea",
      "venue": "Home",
      "competition": "Women's Super League"
    },
    "logo": "manchester-city",
    "league": "premier-league",
    "created_at": "2023-07-01T10:00:00Z",
    "updated_at": "2024-01-15T14:30:00Z"
  },
  {
    "id": 5,
    "name": "Company 1.2",
    "sport": "Football",
    "division": "Development League",
    "organisation_id": 1,
    "organisation_name": "Medinah FC",
    "is_active": true,
    "is_locked": false,
    "parent_squad_id": 4,
    "squad_type": "Development",
    "season": "2023-24",
    "coach": "Mike Johnson",
    "assistant_coach": "Lisa Chen",
    "captain": "Tom Wilson",
    "vice_captain": "Anna Smith",
    "formation": "4-4-2",
    "home_venue": "Development Stadium",
    "training_ground": "Training Center D",
    "squad_size": 22,
    "active_players": 18,
    "injured_players": 1,
    "suspended_players": 0,
    "stats": {
      "matches_played": 12,
      "wins": 7,
      "draws": 3,
      "losses": 2,
      "goals_for": 24,
      "goals_against": 14,
      "points": 24,
      "league_position": 3
    },
    "players": [],
    "recent_form": ["W", "D", "W", "L", "W"],
    "next_match": {
      "date": "2024-01-20",
      "opponent": "Development FC",
      "opponent_logo": "development",
      "venue": "Home",
      "competition": "Development League"
    },
    "logo": "tottenham",
    "league": "premier-league",
    "created_at": "2023-07-01T10:00:00Z",
    "updated_at": "2024-01-15T14:30:00Z"
  },
  {
    "id": 6,
    "name": "Company 1.3",
    "sport": "Football",
    "division": "Academy League",
    "organisation_id": 1,
    "organisation_name": "Medinah FC",
    "is_active": true,
    "is_locked": false,
    "parent_squad_id": 4,
    "squad_type": "Academy",
    "season": "2023-24",
    "coach": "Sarah Davis",
    "assistant_coach": "John Brown",
    "captain": "Emma Taylor",
    "vice_captain": "Jack Miller",
    "formation": "4-3-3",
    "home_venue": "Academy Ground",
    "training_ground": "Youth Academy B",
    "squad_size": 20,
    "active_players": 20,
    "injured_players": 0,
    "suspended_players": 0,
    "stats": {
      "matches_played": 10,
      "wins": 8,
      "draws": 1,
      "losses": 1,
      "goals_for": 28,
      "goals_against": 8,
      "points": 25,
      "league_position": 1
    },
    "players": [],
    "recent_form": ["W", "W", "D", "W", "W"],
    "next_match": {
      "date": "2024-01-21",
      "opponent": "Academy United",
      "opponent_logo": "academy",
      "venue": "Away",
      "competition": "Academy League"
    },
    "logo": "liverpool",
    "league": "premier-league",
    "created_at": "2023-07-01T10:00:00Z",
    "updated_at": "2024-01-15T14:30:00Z"
  },
  {
    "id": 7,
    "name": "Company 2.1",
    "sport": "Football",
    "division": "Reserve League",
    "organisation_id": 1,
    "organisation_name": "Medinah FC",
    "is_active": true,
    "is_locked": false,
    "parent_squad_id": null,
    "squad_type": "Reserve",
    "season": "2023-24",
    "coach": "David Wilson",
    "assistant_coach": "Maria Garcia",
    "captain": "Chris Anderson",
    "vice_captain": "Laura White",
    "formation": "3-5-2",
    "home_venue": "Reserve Stadium",
    "training_ground": "Training Center E",
    "squad_size": 24,
    "active_players": 20,
    "injured_players": 2,
    "suspended_players": 0,
    "stats": {
      "matches_played": 14,
      "wins": 9,
      "draws": 3,
      "losses": 2,
      "goals_for": 32,
      "goals_against": 16,
      "points": 30,
      "league_position": 2
    },
    "players": [],
    "recent_form": ["W", "W", "D", "W", "L"],
    "next_match": {
      "date": "2024-01-22",
      "opponent": "Reserve City",
      "opponent_logo": "reserve",
      "venue": "Home",
      "competition": "Reserve League"
    },
    "logo": "manchester-city",
    "league": "premier-league",
    "created_at": "2023-07-01T10:00:00Z",
    "updated_at": "2024-01-15T14:30:00Z"
  },
  {
    "id": 8,
    "name": "Company 2.2",
    "sport": "Football",
    "division": "Development League",
    "organisation_id": 1,
    "organisation_name": "Medinah FC",
    "is_active": true,
    "is_locked": false,
    "parent_squad_id": 7,
    "squad_type": "Development",
    "season": "2023-24",
    "coach": "Alex Thompson",
    "assistant_coach": "Jenny Lee",
    "captain": "Ryan Murphy",
    "vice_captain": "Sophie Clarke",
    "formation": "4-2-3-1",
    "home_venue": "Development Ground",
    "training_ground": "Training Center F",
    "squad_size": 21,
    "active_players": 19,
    "injured_players": 1,
    "suspended_players": 0,
    "stats": {
      "matches_played": 11,
      "wins": 6,
      "draws": 4,
      "losses": 1,
      "goals_for": 22,
      "goals_against": 12,
      "points": 22,
      "league_position": 4
    },
    "players": [],
    "recent_form": ["D", "W", "D", "W", "D"],
    "next_match": {
      "date": "2024-01-23",
      "opponent": "Development United",
      "opponent_logo": "development",
      "venue": "Away",
      "competition": "Development League"
    },
    "logo": "everton",
    "league": "premier-league",
    "created_at": "2023-07-01T10:00:00Z",
    "updated_at": "2024-01-15T14:30:00Z"
  },
  {
    "id": 9,
    "name": "Company 2.3",
    "sport": "Football",
    "division": "Youth League",
    "organisation_id": 1,
    "organisation_name": "Medinah FC",
    "is_active": true,
    "is_locked": false,
    "parent_squad_id": 7,
    "squad_type": "Youth",
    "season": "2023-24",
    "coach": "Tom Mitchell",
    "assistant_coach": "Kate Wilson",
    "captain": "Jake Roberts",
    "vice_captain": "Mia Johnson",
    "formation": "4-4-2",
    "home_venue": "Youth Stadium",
    "training_ground": "Youth Academy C",
    "squad_size": 19,
    "active_players": 18,
    "injured_players": 0,
    "suspended_players": 0,
    "stats": {
      "matches_played": 9,
      "wins": 7,
      "draws": 1,
      "losses": 1,
      "goals_for": 26,
      "goals_against": 9,
      "points": 22,
      "league_position": 2
    },
    "players": [],
    "recent_form": ["W", "W", "D", "W", "L"],
    "next_match": {
      "date": "2024-01-24",
      "opponent": "Youth Academy",
      "opponent_logo": "youth",
      "venue": "Home",
      "competition": "Youth League"
    },
    "logo": "leeds-united",
    "league": "premier-league",
    "created_at": "2023-07-01T10:00:00Z",
    "updated_at": "2024-01-15T14:30:00Z"
  },
  {
    "id": 10,
    "name": "Company 3.1",
    "sport": "Football",
    "division": "Senior League",
    "organisation_id": 1,
    "organisation_name": "Medinah FC",
    "is_active": true,
    "is_locked": false,
    "parent_squad_id": null,
    "squad_type": "Senior",
    "season": "2023-24",
    "coach": "Roberto Martinez",
    "assistant_coach": "Sarah Johnson",
    "captain": "James Wilson",
    "vice_captain": "Elena Rodriguez",
    "formation": "4-3-3",
    "home_venue": "Senior Stadium",
    "training_ground": "Training Center G",
    "squad_size": 26,
    "active_players": 22,
    "injured_players": 2,
    "suspended_players": 0,
    "stats": {
      "matches_played": 16,
      "wins": 12,
      "draws": 2,
      "losses": 2,
      "goals_for": 38,
      "goals_against": 14,
      "points": 38,
      "league_position": 1
    },
    "players": [],
    "recent_form": ["W", "W", "D", "W", "W"],
    "next_match": {
      "date": "2024-01-25",
      "opponent": "Senior United",
      "opponent_logo": "senior",
      "venue": "Away",
      "competition": "Senior League"
    },
    "logo": "arsenal",
    "league": "premier-league",
    "created_at": "2023-07-01T10:00:00Z",
    "updated_at": "2024-01-15T14:30:00Z"
  },
  {
    "id": 11,
    "name": "Company 3.2",
    "sport": "Football",
    "division": "Development League",
    "organisation_id": 1,
    "organisation_name": "Medinah FC",
    "is_active": true,
    "is_locked": false,
    "parent_squad_id": 10,
    "squad_type": "Development",
    "season": "2023-24",
    "coach": "Lisa Rodriguez",
    "assistant_coach": "Mike Stevens",
    "captain": "Emma Thompson",
    "vice_captain": "Amy Johnson",
    "formation": "4-3-3",
    "home_venue": "Development Stadium B",
    "training_ground": "Training Center H",
    "squad_size": 23,
    "active_players": 20,
    "injured_players": 1,
    "suspended_players": 0,
    "stats": {
      "matches_played": 13,
      "wins": 8,
      "draws": 3,
      "losses": 2,
      "goals_for": 30,
      "goals_against": 18,
      "points": 27,
      "league_position": 3
    },
    "players": [],
    "recent_form": ["W", "D", "W", "L", "W"],
    "next_match": {
      "date": "2024-01-26",
      "opponent": "Development City",
      "opponent_logo": "development",
      "venue": "Home",
      "competition": "Development League"
    },
    "logo": "chelsea",
    "league": "premier-league",
    "created_at": "2023-07-01T10:00:00Z",
    "updated_at": "2024-01-15T14:30:00Z"
  },
  {
    "id": 12,
    "name": "Company 3.3",
    "sport": "Football",
    "division": "Academy League",
    "organisation_id": 1,
    "organisation_name": "Medinah FC",
    "is_active": true,
    "is_locked": false,
    "parent_squad_id": 10,
    "squad_type": "Academy",
    "season": "2023-24",
    "coach": "Kate Wilson",
    "assistant_coach": "David Chen",
    "captain": "Sophie Martinez",
    "vice_captain": "Tom Anderson",
    "formation": "4-2-3-1",
    "home_venue": "Academy Stadium B",
    "training_ground": "Youth Academy D",
    "squad_size": 20,
    "active_players": 19,
    "injured_players": 0,
    "suspended_players": 0,
    "stats": {
      "matches_played": 10,
      "wins": 8,
      "draws": 1,
      "losses": 1,
      "goals_for": 29,
      "goals_against": 10,
      "points": 25,
      "league_position": 1
    },
    "players": [],
    "recent_form": ["W", "W", "D", "W", "W"],
    "next_match": {
      "date": "2024-01-27",
      "opponent": "Academy City",
      "opponent_logo": "academy",
      "venue": "Away",
      "competition": "Academy League"
    },
    "logo": "manchester-united",
    "league": "premier-league",
    "created_at": "2023-07-01T10:00:00Z",
    "updated_at": "2024-01-15T14:30:00Z"
  }
]